minique/__init__.py
minique/api.py
minique/cli.py
minique/compat.py
minique/consts.py
minique/encoding.py
minique/enums.py
minique/excs.py
minique/py.typed
minique/testing.py
minique/types.py
minique/models/__init__.py
minique/models/job.py
minique/models/queue.py
minique/utils/__init__.py
minique/utils/redis_list.py
minique/work/__init__.py
minique/work/job_runner.py
minique/work/worker.py
minique-0.9.1.dist-info/METADATA
minique-0.9.1.dist-info/WHEEL
minique-0.9.1.dist-info/entry_points.txt
minique-0.9.1.dist-info/licenses/LICENSE
minique-0.9.1.dist-info/RECORD
