Metadata-Version: 2.1
Name: minique
Version: 0.9.1
Summary: Minimal Redis job runner
Project-URL: Homepage, https://github.com/valohai/minique
Author-email: Valohai <hait@valohai.com>
License-Expression: MIT
License-File: LICENSE
Requires-Python: >=3.7
Requires-Dist: redis>=2.10.0
Provides-Extra: sentry
Requires-Dist: sentry-sdk~=1.10; extra == 'sentry'
Provides-Extra: test
Requires-Dist: pytest-cov; extra == 'test'
Requires-Dist: pytest>=6; extra == 'test'
